boardom/__init__.py
boardom/version.py
boardom/apis/__init__.py
boardom/apis/dataset.py
boardom/apis/init.py
boardom/apis/layers.py
boardom/apis/optim.py
boardom/apis/resnet.py
boardom/apis/unet.py
boardom/assets/__init__.py
boardom/assets/ballroom_1k.hdr
boardom/assets/cameraman.tif
boardom/assets/cat.png
boardom/assets/peppers.png
boardom/assets/pu_space.pth
boardom/assets/pu_spline_coeffs.pth
boardom/assets/venice_sunset_1k.hdr
boardom/board/__init__.py
boardom/board/main.py
boardom/board/dist/favicon.ico
boardom/board/dist/index.bundle.js
boardom/board/dist/index.html
boardom/board/server/__init__.py
boardom/board/server/common.py
boardom/board/server/data_mixin.py
boardom/board/server/datastore.py
boardom/board/server/server.py
boardom/board/server/socket_manager.py
boardom/components/__init__.py
boardom/components/checkpointer.py
boardom/components/criteria.py
boardom/components/data.py
boardom/components/device.py
boardom/components/image_sampler.py
boardom/components/logger.py
boardom/components/models.py
boardom/components/optimizers.py
boardom/components/sgd.py
boardom/components/util.py
boardom/config/__init__.py
boardom/config/autoconfig.py
boardom/config/cfg_file_parser.py
boardom/config/common.py
boardom/config/config.py
boardom/config/git.py
boardom/config/gitignore.py
boardom/config/session_helpers.py
boardom/data/__init__.py
boardom/data/directory.py
boardom/data/grow.py
boardom/data/list.py
boardom/data/loaded.py
boardom/data/places.py
boardom/engine/__init__.py
boardom/engine/action.py
boardom/engine/cleanup_context.py
boardom/engine/engine.py
boardom/engine/event.py
boardom/engine/middleware.py
boardom/engine/on_decorator.py
boardom/engine/state.py
boardom/external/__init__.py
boardom/external/accuracy.py
boardom/external/compose.py
boardom/external/fftconv2d.py
boardom/imaging/__init__.py
boardom/imaging/colorspaces.py
boardom/imaging/fft.py
boardom/imaging/hdr.py
boardom/imaging/misc.py
boardom/imaging/resize.py
boardom/imaging/tone_map.py
boardom-0.4.4.dist-info/LICENSE
boardom-0.4.4.dist-info/METADATA
boardom-0.4.4.dist-info/WHEEL
boardom-0.4.4.dist-info/entry_points.txt
boardom-0.4.4.dist-info/top_level.txt
boardom-0.4.4.dist-info/RECORD
