Metadata-Version: 2.1
Name: boardom
Version: 0.4.4
Summary: Deep learning toolbox/framework.
Home-page: https://github.com/dmarnerides/boardom
Author: Demetris Marnerides
Author-email: dmarnerides@gmail.com
License: BSD
Platform: UNKNOWN
